[{
  "name" : "Stage Deli",
  "categorycount" : 10
}, {
  "name" : "Binion's Hotel & Casino",
  "categorycount" : 10
}, {
  "name" : "Flux",
  "categorycount" : 9
}, {
  "name" : "Waterstones",
  "categorycount" : 9
}, {
  "name" : "Southwest Institute of Healing Arts",
  "categorycount" : 9
}, {
  "name" : "Hotel du Vin & Bistro Edinburgh",
  "categorycount" : 9
}, {
  "name" : "Tuesday Morning",
  "categorycount" : 9
}, {
  "name" : "MADE Art Boutique",
  "categorycount" : 9
}, {
  "name" : "Jillian's",
  "categorycount" : 9
}, {
  "name" : "Elixir",
  "categorycount" : 9
}]